panel/.bokeh
panel/.eslintrc.js
panel/__init__.py
panel/__main__.py
panel/__version.py
panel/_param.py
panel/_version.py
panel/auth.py
panel/bokeh.ext.json
panel/compiler.py
panel/config.py
panel/custom.py
panel/depends.py
panel/entry_points.py
panel/index.ts
panel/interact.py
panel/links.py
panel/package-lock.json
panel/package.json
panel/param.py
panel/pipeline.py
panel/py.typed
panel/reactive.py
panel/tsconfig.json
panel/viewable.py
panel/_templates/autoload_panel_js.js
panel/_templates/base.html
panel/_templates/basic_login.html
panel/_templates/convert_index.html
panel/_templates/doc_nb_js.js
panel/_templates/error.html
panel/_templates/index.html
panel/_templates/js_resources.html
panel/_templates/jupyter.css
panel/_templates/kernel_error.html
panel/_templates/logout.html
panel/_templates/nb_template.html
panel/_templates/pyodide_handler.js
panel/_templates/pyodide_worker.js
panel/_templates/serviceWorker.js
panel/_templates/site.webmanifest
panel/chat/__init__.py
panel/chat/_param.py
panel/chat/feed.py
panel/chat/icon.py
panel/chat/input.py
panel/chat/interface.py
panel/chat/langchain.py
panel/chat/message.py
panel/chat/step.py
panel/chat/utils.py
panel/command/__init__.py
panel/command/bundle.py
panel/command/compile.py
panel/command/convert.py
panel/command/oauth_secret.py
panel/command/serve.py
panel/io/__init__.py
panel/io/admin.py
panel/io/application.py
panel/io/browser.py
panel/io/cache.py
panel/io/callbacks.py
panel/io/compile.py
panel/io/convert.py
panel/io/datamodel.py
panel/io/django.py
panel/io/document.py
panel/io/embed.py
panel/io/fastapi.py
panel/io/handlers.py
panel/io/ipywidget.py
panel/io/jupyter_executor.py
panel/io/jupyter_server_extension.py
panel/io/liveness.py
panel/io/loading.py
panel/io/location.py
panel/io/logging.py
panel/io/mime_render.py
panel/io/model.py
panel/io/notebook.py
panel/io/notifications.py
panel/io/profile.py
panel/io/pyodide.py
panel/io/reload.py
panel/io/resources.py
panel/io/rest.py
panel/io/save.py
panel-1.8.0.dist-info/METADATA
panel-1.8.0.dist-info/WHEEL
panel-1.8.0.dist-info/entry_points.txt
panel-1.8.0.dist-info/licenses/LICENSE.txt
panel-1.8.0.dist-info/RECORD
