Metadata-Version: 2.4
Name: panel
Version: 1.8.0
Summary: The powerful data exploration & web app framework for Python.
Project-URL: Homepage, https://panel.holoviz.org
Project-URL: Source, https://github.com/holoviz/panel
Project-URL: HoloViz, https://holoviz.org/
Author-email: HoloViz developers <developers@holoviz.org>
Maintainer-email: HoloViz developers <developers@holoviz.org>
License: BSD
License-File: LICENSE.txt
Classifier: Development Status :: 5 - Production/Stable
Classifier: Intended Audience :: Developers
Classifier: Intended Audience :: Financial and Insurance Industry
Classifier: Intended Audience :: Healthcare Industry
Classifier: Intended Audience :: Information Technology
Classifier: Intended Audience :: Legal Industry
Classifier: Intended Audience :: Other Audience
Classifier: Intended Audience :: Science/Research
Classifier: License :: OSI Approved :: BSD License
Classifier: Natural Language :: English
Classifier: Operating System :: OS Independent
Classifier: Programming Language :: Python :: 3
Classifier: Programming Language :: Python :: 3.10
Classifier: Programming Language :: Python :: 3.11
Classifier: Programming Language :: Python :: 3.12
Classifier: Programming Language :: Python :: 3.13
Classifier: Topic :: Office/Business
Classifier: Topic :: Office/Business :: Financial
Classifier: Topic :: Scientific/Engineering
Classifier: Topic :: Scientific/Engineering :: Information Analysis
Classifier: Topic :: Scientific/Engineering :: Visualization
Classifier: Topic :: Software Development :: Libraries
Requires-Python: >=3.10
Requires-Dist: bleach
Requires-Dist: bokeh<3.9.0,>=3.7.0
Requires-Dist: linkify-it-py
Requires-Dist: markdown
Requires-Dist: markdown-it-py
Requires-Dist: mdit-py-plugins
Requires-Dist: packaging
Requires-Dist: pandas>=1.2
Requires-Dist: param<3.0,>=2.1.0
Requires-Dist: pyviz-comms>=2.0.0
Requires-Dist: requests
Requires-Dist: tqdm
Requires-Dist: typing-extensions
Provides-Extra: dev
Requires-Dist: watchfiles; extra == 'dev'
Provides-Extra: fastapi
Requires-Dist: bokeh-fastapi<0.2.0,>=0.1.2; extra == 'fastapi'
Requires-Dist: fastapi[standard]; extra == 'fastapi'
Provides-Extra: mypy
Requires-Dist: mypy; extra == 'mypy'
Requires-Dist: pandas-stubs; extra == 'mypy'
Requires-Dist: types-bleach; extra == 'mypy'
Requires-Dist: types-croniter; extra == 'mypy'
Requires-Dist: types-markdown; extra == 'mypy'
Requires-Dist: types-psutil; extra == 'mypy'
Requires-Dist: types-requests; extra == 'mypy'
Requires-Dist: types-tqdm; extra == 'mypy'
Requires-Dist: typing-extensions; extra == 'mypy'
Provides-Extra: recommended
Requires-Dist: holoviews>=1.18.0; extra == 'recommended'
Requires-Dist: jupyterlab; extra == 'recommended'
Requires-Dist: matplotlib; extra == 'recommended'
Requires-Dist: pillow; extra == 'recommended'
Requires-Dist: plotly; extra == 'recommended'
Provides-Extra: tests
Requires-Dist: psutil; extra == 'tests'
Requires-Dist: pytest; extra == 'tests'
Requires-Dist: pytest-asyncio; extra == 'tests'
Requires-Dist: pytest-rerunfailures<16.0; extra == 'tests'
Requires-Dist: pytest-xdist; extra == 'tests'
